conda_inject/__init__.py
conda_inject-1.3.1.dist-info/LICENSE
conda_inject-1.3.1.dist-info/METADATA
conda_inject-1.3.1.dist-info/WHEEL
conda_inject-1.3.1.dist-info/RECORD
